<BackupInst xmlns="http://www.microsoft.com/GroupPolicy/GPOOperations/Manifest"><GPOGuid><![CDATA[{CF2F9BB3-8E13-45F8-A0F2-E5BF6D384DF8}]]></GPOGuid><GPODomain><![CDATA[eprg.local]]></GPODomain><GPODomainGuid><![CDATA[{5d1e523f-7ae4-437f-9528-6cd7165d12b7}]]></GPODomainGuid><GPODomainController><![CDATA[WIN-6QOO5LNKM7T.eprg.local]]></GPODomainController><BackupTime><![CDATA[2023-10-02T20:27:44]]></BackupTime><ID><![CDATA[{7A2C83CD-15F7-403E-A409-504029F73F3E}]]></ID><Comment><![CDATA[]]></Comment><GPODisplayName><![CDATA[ADDS (LDAP)]]></GPODisplayName></BackupInst>
